url_downloader/__init__.py
url_downloader/url_downloader.py
url_downloader-1.0.5.dist-info/LICENSE
url_downloader-1.0.5.dist-info/METADATA
url_downloader-1.0.5.dist-info/WHEEL
url_downloader-1.0.5.dist-info/top_level.txt
url_downloader-1.0.5.dist-info/RECORD
