Metadata-Version: 2.1
Name: url-downloader
Version: 1.0.5
Summary: Simplify retrieving or downloading data from any url.
Home-page: https://github.com/ChsHub/url_downloader
Author: ChsHub
License: MIT License
Classifier: Programming Language :: Python :: 3.7
License-File: LICENSE
Requires-Dist: requests
